[{"name":"RBCodeCruftLeftInMethodsRule","severity":"error","group":"Bugs","critics":[{"package":"Kernel","name":"DelayExperimentalSpinScheduler>>#schedule:"},{"package":"Kernel","name":"DelayExperimentalSpinScheduler>>#unschedule:"},{"package":"Glamour-Morphic-Brick","name":"GLMBrick>>#drawSubmorphsOn:"},{"package":"Glamour-Morphic-Brick","name":"GLMBrick>>#drawSubmorphsOnAthensCanvas:"},{"package":"GT-Spotter","name":"GTSpotterProcessor>>#exceptionHandler"},{"package":"Keymapping-KeyCombinations","name":"KeyboardEvent>>#modifiedCharacter"},{"package":"Reflectivity-Tests","name":"CoverageDemoTest>>#testCoverageControlFlow"},{"package":"NativeBoost-Core","name":"NBNativeCodeGen class>>#generateCode:andRetry:"},{"package":"RPackage-Tests","name":"RPackageCategorySynchronisationTest>>#testAddCategoryCreatesPackage"},{"package":"RPackage-Tests","name":"RPackageCategorySynchronisationTest>>#testAddCategoryIsAlreadyAPackageDoesNotCreatePackage"},{"package":"MonticelloGUI","name":"MCWorkingCopyBrowser>>#editRepository"},{"package":"Tool-ProcessBrowser","name":"ProcessBrowser class>>#dumpTallyOnTranscript:"},{"package":"CodeImport","name":"FileCompilerRequestor>>#notify:at:in:"},{"package":"Spec-Core","name":"TreeModel class>>#example"},{"package":"Spec-Core","name":"TreeModel class>>#exampleWithCustomColumnsAndNodes"},{"package":"Spec-Core","name":"TreeModel class>>#exampleWithCustomColumnsAndNodesAndChildren"},{"package":"AsmJit-x86","name":"AJx86Registers class>>#code:"},{"package":"Glamour-Rubric-Presentations","name":"GLMHighlighterTextParserStyler>>#privateFormat:"},{"package":"Glamour-Rubric-Presentations","name":"GLMHighlighterTextParserStyler>>#privateStyle:"},{"package":"GT-SpotterExtensions-Core","name":"GTFilterFileReference>>#queryForItem:"},{"package":"CollectionsTests","name":"DictionaryTest>>#expectedSizeAfterReject"},{"package":"Glamour-Morphic-Brick","name":"GLMMorphBrick>>#drawSubmorphsOn:"},{"package":"GT-Spotter","name":"GTSpotterItemBrick>>#newLabelBrick"},{"package":"RPackage-Core","name":"RPackage>>#updateDefinedClassNamed:withNewName:"},{"package":"GT-SpotterExtensions-Core","name":"RPackage>>#spotterPreviewCodeIn:"},{"package":"RPackage-Core","name":"RPackage>>#extensionClasses"},{"package":"RPackage-Core","name":"RPackage>>#classesAndMetaClasses"},{"package":"RPackage-Core","name":"RPackage>>#extensionCategoriesForClass:"},{"package":"RPackage-Core","name":"RPackage>>#includesMethod:ofClass:"},{"package":"RPackage-Core","name":"RPackage>>#coreCategoriesForClass:"},{"package":"Glamour-Morphic-Renderer","name":"GLMMorphicRubricTextRenderer>>#morph"},{"package":"Refactoring-Tests-Critics","name":"RBSmalllintTestObject>>#codeCruftLeftInMethods"},{"package":"Refactoring-Tests-Critics","name":"RBSmalllintTestObject>>#debbuggingMessageSent"},{"package":"Refactoring-Tests-Critics","name":"RBSmalllintTestObject>>#haltClassMentioned"},{"package":"Refactoring-Tests-Critics","name":"RBSmalllintTestObject>>#transcriptMentioned"},{"package":"Refactoring-Tests-Critics","name":"RBSmalllintTestObject>>#flagged"},{"package":"Kernel","name":"Random class>>#bucketTest:"},{"package":"GT-SpotterExtensions-Core","name":"MCWorkingCopy>>#spotterAncestorsFor:"},{"package":"GT-SpotterExtensions-Core","name":"MCWorkingCopy>>#spotterPackageFor:"},{"package":"Glamour-Morphic-Widgets","name":"LazyTabGroupMorph>>#updatePageIndex:"},{"package":"Refactoring-Tests-Core","name":"RBRefactoryTestDataApp>>#cruft"},{"package":"Reflectivity","name":"RFASTTranslator>>#visitBlockNode:"},{"package":"Reflectivity","name":"RFASTTranslator>>#visitMethodNode:"},{"package":"Morphic-Base","name":"TableLayout>>#computeGlobalCellArrangement:in:horizontal:wrap:spacing:"},{"package":"Morphic-Base","name":"TableLayout>>#indexForInserting:inList:horizontal:target:"},{"package":"GT-SpotterExtensions-Core","name":"ThemeIcons>>#spotterForIconsFor:"},{"package":"Glamour-Morphic-Brick","name":"GLMBrickGeometryTrait>>#extent:"},{"package":"Versionner-Core-Model","name":"MBConfigurationRoot>>#categoryModified:"},{"package":"Network-Kernel","name":"SocketStream class>>#finger:"},{"package":"Glamour-Morphic-Brick","name":"GLMCompositeBrick>>#custom:"},{"package":"RPackage-Core","name":"RPackageOrganizer>>#systemClassRenamedActionFrom:"},{"package":"RPackage-Core","name":"RPackageOrganizer>>#systemMethodModifiedActionFrom:"},{"package":"RPackage-Core","name":"RPackageOrganizer>>#systemCategoryRemovedActionFrom:"},{"package":"RPackage-Core","name":"RPackageOrganizer>>#packageOfClassNamed:"},{"package":"RPackage-Core","name":"RPackageOrganizer>>#registerInterestToAnnouncer:"},{"package":"Compiler","name":"ReturnNode>>#analyseTempsWithin:rootNode:assignmentPools:"},{"package":"Kernel","name":"UnhandledError>>#defaultAction"},{"package":"Debugger-Tests","name":"FilterTest>>#setUp"},{"package":"Ring-Core-Containers","name":"RGContainer>>#addClass:"},{"package":"Ring-Core-Containers","name":"RGContainer>>#includesClassNamed:"},{"package":"Athens-Morphic","name":"AthensCanvasWrapper>>#image:at:sourceRect:rule:"},{"package":"Athens-Morphic","name":"AthensCanvasWrapper>>#drawString:in:font:color:"},{"package":"Athens-Morphic","name":"AthensCanvasWrapper>>#fillColor:"},{"package":"Athens-Morphic","name":"AthensCanvasWrapper>>#cache:using:during:"},{"package":"Athens-Morphic","name":"AthensCanvasWrapper>>#asShadowDrawingCanvas"},{"package":"Collections-Streams","name":"Generator class>>#examplePrimes"},{"package":"FileSystem-Tests-Core","name":"FileSystemHandleTest>>#testCreatedOpen"},{"package":"Morphic-Examples","name":"TabExample>>#freshListTab"},{"package":"Tool-Base","name":"PasteUpMorph>>#defaultDesktopCommandKeyTriplets"},{"package":"Spec-Core","name":"NewListModel class>>#exampleWithMenu"},{"package":"NautilusRefactoring","name":"EnvironmentChooser>>#chooseNewEnvironment"},{"package":"Glamour-Examples","name":"GLMExamplesBrowser>>#exampleIn:"},{"package":"Morphic-Base","name":"TextMorph>>#passKeyboardFocusTo:"},{"package":"OpalCompiler-Tests","name":"OCCompilerNotifyingTest>>#testTooManyTemporaries"},{"package":"OpalCompiler-Tests","name":"OCCompilerNotifyingTest>>#testEmptyCaseStatement"},{"package":"GT-SpotterExtensions-Core","name":"GTFilterImplementor>>#itemFilterNameFor:"},{"package":"ConfigurationCommandLineHandler-Core","name":"ConfigurationCommandLineHandler>>#hasConfiguration"},{"package":"NativeBoost-Tests","name":"NBExternalEnumTests>>#primExecuteCallbackEnumReturn:"},{"package":"CompressionTests","name":"ZipArchiveTest>>#testCreateWithRelativeNames"},{"package":"CompressionTests","name":"ZipArchiveTest>>#testZip"},{"package":"Metacello-MC","name":"MetacelloMCProjectSpec>>#loadVersion:"},{"package":"Metacello-MC","name":"MetacelloMCProjectSpec>>#version"},{"package":"Reflectivity","name":"HookGenerator>>#preamble"},{"package":"Compiler","name":"EncoderForV3>>#genSend:numArgs:"},{"package":"Compression","name":"ZipArchiveMember>>#desiredCompressionMethod:"},{"package":"Compression","name":"ZipArchiveMember>>#refreshLocalFileHeaderTo:"},{"package":"GT-SpotterExtensions-Core","name":"FileReference>>#spotterPreviewItemsIn:"},{"package":"GT-SpotterExtensions-Core","name":"MCVersionInfo>>#spotterAncestorsFor:"},{"package":"Tool-Base","name":"MethodClassifier>>#classifyByOtherImplementors:"},{"package":"Glamour-Morphic-Theme","name":"GLMWhitespaceTheme>>#windowEdgeNormalFillStyleFor:"},{"package":"Glamour-Morphic-Theme","name":"GLMWhitespaceTheme>>#resizerGripNormalFillStyleFor:"},{"package":"Text-Core","name":"TextMethodLink>>#actOnClick:for:in:editor:"},{"package":"Graphics-Canvas","name":"PluggableCanvas>>#fillOval:fillStyle:borderWidth:borderColor:"},{"package":"Metacello-ToolBox","name":"MetacelloToolBox class>>#releaseEarlyAccessVersion:for:from:"},{"package":"Morphic-Core","name":"HandMorph>>#generateKeyboardEvent:"},{"package":"Morphic-Widgets-NewList","name":"NewListAdapter>>#getHeaderHeight"},{"package":"Reflectivity","name":"Breakpoint>>#haltNow"},{"package":"KernelTests","name":"DelayBenchmark class>>#runAll"},{"package":"NECompletion","name":"NECMenuMorph>>#drawModelMessageOn:in:"},{"package":"NECompletion","name":"NECMenuMorph>>#insertCommonPrefix"},{"package":"NECompletion","name":"NECMenuMorph>>#detailMessage"},{"package":"NECompletion","name":"NECMenuMorph>>#insertCommonPrefixOrSelected"},{"package":"NECompletion","name":"NECMenuMorph>>#mouseDown:"},{"package":"Compiler","name":"Encoder>>#bindTemp:in:"},{"package":"Spec-Core","name":"ComposableModel>>#private_buildWithSpec:"},{"package":"FileSystem-Disk","name":"DiskStore>>#isReadable:"},{"package":"FileSystem-Disk","name":"DiskStore>>#isWritable:"},{"package":"NativeBoost-Core","name":"NBNativeCodeGen>>#generatedCode"},{"package":"Compression","name":"ZipNewFileMember>>#from:"},{"package":"RPackage-Tests","name":"RPackageMonticelloSynchronisationTest>>#testUnloadMCPackageRemovesRPackage"},{"package":"FuelTests","name":"FLInMemoryBasicSerializationTest>>#testStringGlobalsAndClosure"},{"package":"OpalCompiler-Core","name":"RBMethodNode>>#tempNames"},{"package":"StartupPreferences","name":"StartupPreferencesHandler>>#lookInFolder:"},{"package":"TxText-Model","name":"TxModel>>#postCopy"},{"package":"CodeImport","name":"CodeImporter>>#selectTextConverterForCode"},{"package":"CodeImport","name":"DoItChunk>>#importFor:"},{"package":"TxText-Athens","name":"TxBlockCursor>>#drawOnAthensCanvas:"},{"package":"TxText-Athens","name":"TxCharacterSpanDisplayCommand>>#contains:"},{"package":"Nautilus","name":"PackageTreeNautilusUI>>#registerSelectionGroup:"},{"package":"Morphic-Core","name":"WorldState>>#interCyclePause:"},{"package":"Morphic-Core","name":"WorldState>>#runStepMethodsIn:"},{"package":"Flashback-Decompiler-Tests","name":"FBDExamples>>#nestedBlocksRemoteInBlockCase2"},{"package":"Flashback-Decompiler-Tests","name":"FBDExamples>>#nestedBlocksRemoteInBlockCase3"},{"package":"Flashback-Decompiler-Tests","name":"FBDExamples>>#examplePushBigArray"},{"package":"Flashback-Decompiler-Tests","name":"FBDExamples>>#exampleToDoInsideBlock"},{"package":"Flashback-Decompiler-Tests","name":"FBDExamples>>#nestedBlocksRemoteInBlockCase1"},{"package":"FileSystem-Core","name":"PlatformResolver class>>#primitiveGetUntrustedUserDirectory"},{"package":"FileSystem-Disk","name":"WindowsStore class>>#maxFileNameLength"},{"package":"Rubric","name":"RubTextAreaExamples class>>#textFieldWithCRAction"},{"package":"Collections-Abstract","name":"Collection>>#includesAnyOf:"},{"package":"Collections-Abstract","name":"Collection>>#includesAllOf:"},{"package":"Graphics-Canvas","name":"FormCanvas>>#fillOval:fillStyle:borderWidth:borderColor:"},{"package":"KernelTests","name":"ProtoObjectTest>>#testIfNotNil"},{"package":"KernelTests","name":"ProtoObjectTest>>#testFlag"},{"package":"KernelTests","name":"ProtoObjectTest>>#testIfNil"},{"package":"KernelTests","name":"ProtoObjectTest>>#testIfNotNilIfNil"},{"package":"KernelTests","name":"ProtoObjectTest>>#testIfNilIfNotNil"},{"package":"System-Hashing","name":"DigitalSignatureAlgorithm>>#isProbablyPrime:"},{"package":"System-Hashing","name":"DigitalSignatureAlgorithm>>#generateKeySet"},{"package":"Keymapping-Core","name":"KMCategoryTarget>>#verifyMatchWith:notifying:thenDoing:"},{"package":"MonticelloConfigurations","name":"MCConfiguration class>>#whatChangedFrom:to:"},{"package":"Morphic-Widgets-List","name":"TreeListMorph>>#addSubmorphsAfter:fromCollection:allowSorting:"},{"package":"Glamour-Morphic-Brick","name":"GLMStringBrick>>#onDrawAthensCanvas:"},{"package":"RPackage-Core","name":"CompiledMethod>>#packageFromOrganizer:"},{"package":"GT-SpotterExtensions-Core","name":"CompiledMethod>>#spotterPreviewCodeIn:"},{"package":"KernelTests","name":"CodeSimulationTests>>#methodWithHalt"},{"package":"KernelTests","name":"CodeSimulationTests>>#methodWithTranscript"},{"package":"Slot-Tests","name":"SlotErrorsTest>>#assertInvalidClassName:"},{"package":"Monticello","name":"MCCacheRepository class>>#default"},{"package":"TxText-Styler","name":"TxTextStyler>>#resolveStyleFor:"},{"package":"Zinc-HTTP","name":"ZnLogEvent class>>#logToTranscript"},{"package":"Morphic-Base","name":"PluggableMenuSpec class>>#exampleWithOneSingleItem"},{"package":"Morphic-Base","name":"PluggableMenuSpec class>>#exampleWithTwoSimpleItems"},{"package":"Graphics-Canvas","name":"MultiCanvas>>#apply:"},{"package":"Athens-Balloon","name":"AthensBalloonStrokePaint>>#capRound"},{"package":"Athens-Balloon","name":"AthensBalloonStrokePaint>>#capButt"},{"package":"Athens-Balloon","name":"AthensBalloonStrokePaint>>#capSquare"},{"package":"Athens-Balloon","name":"AthensBalloonStrokePaint>>#joinRound"},{"package":"Athens-Balloon","name":"AthensBalloonStrokePaint>>#joinMiter"},{"package":"Athens-Balloon","name":"AthensBalloonStrokePaint>>#joinBevel"},{"package":"Flashback-Decompiler","name":"FBDDecompiler>>#skipTemps:"},{"package":"Graphics-Primitives","name":"ColorMap>>#mappingTo:"},{"package":"Keymapping-Core","name":"KMCategoryBinding>>#verifyMatchWith:notifying:thenDoing:"},{"package":"Nautilus","name":"AbstractNautilusUI>>#moveInPackage"},{"package":"Nautilus","name":"AbstractNautilusUI>>#textMorphClass"},{"package":"System-Support","name":"SmalltalkImage>>#associationAt:ifAbsent:"},{"package":"System-Support","name":"SmalltalkImage>>#select:"},{"package":"System-Support","name":"SmalltalkImage>>#includes:"},{"package":"System-Support","name":"SmalltalkImage>>#keys"},{"package":"System-Support","name":"SmalltalkImage>>#logChange:"},{"package":"System-Support","name":"SmalltalkImage>>#removeKey:ifAbsent:"},{"package":"System-Support","name":"SmalltalkImage>>#keyAtValue:"},{"package":"System-Support","name":"SmalltalkImage>>#size"},{"package":"System-Support","name":"SmalltalkImage>>#removeKey:"},{"package":"System-Support","name":"SmalltalkImage>>#do:"},{"package":"System-Support","name":"SmalltalkImage>>#keyAtIdentityValue:ifAbsent:"},{"package":"System-Support","name":"SmalltalkImage>>#keysAndValuesDo:"},{"package":"KernelTests","name":"ObjectTest>>#testHaltIf"},{"package":"KernelTests","name":"ObjectTest>>#b1"},{"package":"KernelTests","name":"ObjectTest>>#testHaltOnCount"},{"package":"KernelTests","name":"ObjectTest>>#b"},{"package":"KernelTests","name":"ObjectTest>>#testHaltOnce"},{"package":"Ring-Core-Kernel","name":"RGMethodDefinition>>#isSameRevisionAs:"},{"package":"Ring-Core-Kernel","name":"RGMethodDefinition>>#''<=''"},{"package":"GT-SpotterExtensions-Core","name":"RGMethodDefinition>>#spotterPreviewCodeIn:"},{"package":"Morphic-Base","name":"StringMorphEditor>>#keyStroke:"},{"package":"GT-Inspector","name":"GTSimpleMethodsBrowser>>#updateOuterPaneFrom:for:"},{"package":"Graphics-Display Objects","name":"InfiniteForm>>#displayOnPort:at:"},{"package":"Morphic-Base","name":"StringMorph>>#addOptionalHandlesTo:box:"},{"package":"Spec-Debugger","name":"SpecDebuggerStack>>#contextMenu:"},{"package":"Morphic-Base","name":"HaloMorph>>#popUpFor:event:"},{"package":"Morphic-Base","name":"ToggleMenuItemMorph>>#icon"},{"package":"Glamour-Core","name":"GLMPane>>#postCopy"},{"package":"GT-Spotter","name":"GTSpotterResultsBrick>>#onCandidateSelected:"},{"package":"FileSystem-Memory","name":"MemoryFileSystemFile>>#at:"},{"package":"FuelTests","name":"FLMigrationTest>>#testBadDestinationVariableRename"},{"package":"System-Support","name":"Model>>#hasUnacceptedEdits"},{"package":"Glamour-Core","name":"GLMBrowser>>#resolveDestinationPort:"},{"package":"Glamour-Core","name":"GLMBrowser>>#postCopy"},{"package":"Reflectivity","name":"Slot>>#link:"},{"package":"Morphic-Widgets-FastTable","name":"FTTableContainerMorph>>#fullDrawOn:"},{"package":"Glamour-Morphic-Pager","name":"GLMPagerScrollBrick>>#paneMargin"},{"package":"Glamour-Browsers","name":"GLMFinder>>#passivelyFromPrevious:"},{"package":"Glamour-Browsers","name":"GLMFinder>>#fromPrevious:"},{"package":"NativeBoost-Core","name":"NBNativeFunctionGen>>#generateInstructions:"},{"package":"FuelTests","name":"FLHookedSubstitutionTest>>#testProxyByTargetAnalisysIsPropagated"},{"package":"System-CommandLine","name":"Termcap>>#reset"},{"package":"Slot","name":"PropertySlot>>#layoutChanged:"},{"package":"DebuggerModel","name":"DebugSession>>#unwindAndRestartToContext:"},{"package":"DebuggerModel","name":"DebugSession>>#downInContext:"},{"package":"DebuggerModel","name":"DebugSession>>#returnValueFrom:"},{"package":"DebuggerModel","name":"DebugSession>>#peelToFirstLike:"},{"package":"DebuggerModel","name":"DebugSession>>#returnValue:from:"},{"package":"MonticelloFileTree-Core","name":"MCFileTreeAbstractStWriter>>#visitScriptDefinition:"},{"package":"Fuel","name":"FLPrimitiveCluster>>#registerIndexesOn:"},{"package":"Fuel","name":"FLBitsObjectCluster>>#registerIndexesOn:"},{"package":"Graphics-Canvas","name":"ClippingCanvas>>#contentsOfArea:into:"},{"package":"Text-Edition","name":"Editor>>#setIndices:forward:"},{"package":"Slot","name":"BooleanSlot>>#layoutChanged:"},{"package":"FileSystem-Disk","name":"MacStore>>#mimeTypesAt:"},{"package":"Spec-Debugger","name":"SpecDebugger>>#process:controller:context:"},{"package":"Spec-Debugger","name":"SpecDebugger>>#openFullNoSuspendLabel:"},{"package":"Spec-Debugger","name":"SpecDebugger>>#initializePresenter"},{"package":"Morphic-Base","name":"SystemProgressMorph>>#show:"},{"package":"Morphic-Base","name":"SystemProgressMorph>>#show:from:to:"},{"package":"OpalCompiler-Core","name":"IRJumpIf>>#nextBytecodeOffsetAfterJump"},{"package":"GT-Playground","name":"GLMSystemWindow>>#acceptContents:"},{"package":"GT-Playground","name":"GLMSystemWindow>>#acceptAction:"},{"package":"Traits","name":"TClassDescription>>#noteMethodRemoved:"},{"package":"Traits","name":"TClassDescription>>#noteMethodChanged:to:"},{"package":"ScriptLoader50","name":"ScriptLoader class>>#initialize"},{"package":"TxText-Athens","name":"TxTextAdapter>>#setSelectionFromModel:"},{"package":"TxText-Athens","name":"TxTextAdapter>>#pendingText:"},{"package":"TxText-Athens","name":"TxTextAdapter>>#getText"},{"package":"NautilusRefactoring","name":"ChangesBrowser>>#updateChanges"},{"package":"Monticello","name":"MCDataStream class>>#initialize"},{"package":"Rubric","name":"RubTextMethodLink>>#actOnClick:for:in:editor:"},{"package":"Glamour-Core","name":"GLMTransmission>>#transmitIn:"},{"package":"GT-Tests-Spotter","name":"GTSpotterStepTest>>#testContextChange"},{"package":"GT-Tests-Spotter","name":"GTSpotterStepTest>>#basicSearch:"},{"package":"Files","name":"FileStream class>>#standardIOStreamNamed:forWrite:"},{"package":"GT-SpotterExtensions-Core","name":"GTSpotter>>#spotterStfxFor:"},{"package":"GT-SpotterExtensions-Core","name":"GTSpotter>>#spotterConcreteMethodFor:"},{"package":"GT-SpotterExtensions-Core","name":"GTSpotter>>#spotterForFilesFor:"},{"package":"GT-SpotterExtensions-Core","name":"GTSpotter>>#fileReferencesBy:inContext:usingFilter:"},{"package":"GT-SpotterExtensions-Core","name":"GTSpotter>>#spotterImplementorsFor:"},{"package":"GT-SpotterExtensions-Core","name":"GTSpotter>>#spotterForExpressionsFor:"},{"package":"GT-SpotterExtensions-Core","name":"GTSpotter>>#spotterForDirectoriesFor:"},{"package":"System-Support","name":"VirtualMachine>>#isPharoVM"},{"package":"GT-Spotter","name":"GTSpotterStackedLayout>>#layoutStacked:in:"},{"package":"NautilusCommon","name":"AnnotationPanePlugin>>#buildString"},{"package":"Nautilus","name":"AbstractCategoryWidget>>#categoryIconFor:"},{"package":"Graphics-Primitives","name":"Color>>#isTranslucentColor"},{"package":"KernelTests","name":"UndefinedObjectTest>>#testIfNotNilIfNil"},{"package":"KernelTests","name":"UndefinedObjectTest>>#testIfNilIfNotNil"},{"package":"KernelTests","name":"UndefinedObjectTest>>#testIfNil"},{"package":"NECompletion","name":"FinderUI>>#guessTypeForName:"},{"package":"Spec-Tools","name":"DualChangeSorterApplication class>>#changesListMenu:"},{"package":"Spec-Tools","name":"DualChangeSorterApplication class>>#messageListMenu:"},{"package":"Spec-Tools","name":"DualChangeSorterApplication class>>#classListMenu:"},{"package":"Slot","name":"AbstractClassInstaller>>#installTraitComposition:on:"},{"package":"NativeBoost-Tests","name":"NBMacSpecificTest>>#testSystemCall"},{"package":"Compiler","name":"SelectorNode>>#sizeCode:args:super:"},{"package":"GT-SpotterExtensions-Core","name":"TClass>>#spotterPreviewCodeIn:"},{"package":"Glamour-Morphic-Widgets","name":"GLMTreeMorphModel>>#wantsDroppedMorph:event:inMorph:"},{"package":"Morphic-Widgets-Scrolling","name":"ScrollPane>>#mouseDown:"},{"package":"Versionner-Tests-Core-Model","name":"MBConfigurationRootTest>>#test0050BasicVersionLoad"},{"package":"Glamour-Core","name":"GLMPresentationBoundPort>>#value"},{"package":"Glamour-Presentations","name":"GLMListingPresentation>>#columns"},{"package":"Glamour-Presentations","name":"GLMListingPresentation>>#childrenValueOf:"},{"package":"Glamour-Presentations","name":"GLMListingPresentation>>#childrenValueOf:atLevel:"},{"package":"System-Announcements","name":"ClassCommented class>>#classCommented:"},{"package":"Rubric","name":"RubAbstractTextArea>>#handleSelectionChange:"},{"package":"Manifest-Resources-Tests","name":"MFClassA>>#method"},{"package":"NativeBoost-Core","name":"NBExternalType class>>#pointerSize"},{"package":"Kernel","name":"Context>>#completeCallee:"},{"package":"Refactoring-Tests-Core","name":"RBNamespaceTest>>#testModelImplementorsSenders"},{"package":"Glamour-Core","name":"GLMSingleUpdateAction>>#computeAnnouncerObjects"},{"package":"Tool-Diff","name":"PSMCPatchMorph>>#expandChangeTree"},{"package":"Kernel","name":"Timespan>>#includesAnyOf:"},{"package":"Kernel","name":"Timespan>>#includesAllOf:"},{"package":"Glamour-Morphic-Renderer","name":"GLMMorphicStackerRenderer>>#render:"},{"package":"Kernel","name":"UndefinedObject>>#haltIfNil"},{"package":"Compression","name":"ZipWriteStream>>#flushBlock:"},{"package":"Spec-Layout","name":"SpecLayoutAdd>>#offsets"},{"package":"NECompletion","name":"NECController>>#handleKeystrokeBefore:editor:"},{"package":"CodeImport","name":"EvaluateCommandLineHandler>>#evaluateStdIn"},{"package":"Reflectivity","name":"LinkWrapperGlobal>>#emitValue:"},{"package":"CollectionsTests","name":"TPrintOnSequencedTest>>#testPrintNameOn"},{"package":"Morphic-Core","name":"Morph>>#rootMorphsAt:"},{"package":"Morphic-Core","name":"Morph>>#transferHalo:from:"},{"package":"Morphic-Core","name":"Morph>>#tabHitWithEvent:"},{"package":"GT-Playground","name":"GTPlayPage>>#acceptContents:"},{"package":"GT-SpotterExtensions-Core","name":"GTPlayPage>>#spotterPreviewCodeIn:"},{"package":"NativeBoost-Core","name":"NBFFICallout>>#generateInstructions:"},{"package":"GT-Tests-Spotter","name":"GTSpotterTest>>#testInitialText"},{"package":"GT-Tests-Spotter","name":"GTSpotterTest>>#testEmptyTextInput"},{"package":"SUnit-UITesting","name":"Workspace>>#hasUnacceptedEdits"},{"package":"Morphic-Base","name":"MenuItemMorph>>#invokeWithEvent:"},{"package":"Morphic-Base","name":"MenuItemMorph>>#contents:withMarkers:inverse:"},{"package":"GT-SpotterExtensions-Core","name":"MenuItemMorph>>#spotterPreviewMenuIn:"},{"package":"Slot","name":"UnlimitedInstanceVariableSlot>>#layoutChanged:"},{"package":"Network-Kernel","name":"Socket class>>#loopbackTest"},{"package":"Morphic-Core","name":"WorldState class>>#setHaltOnce"},{"package":"Morphic-Base","name":"WorldState class>>#systemOn:"},{"package":"Morphic-Core","name":"WorldState class>>#clearHaltOnce"},{"package":"Glamour-Morphic-Renderer","name":"GLMMorphicWidgetRenderer>>#morph:withTitleOf:"},{"package":"Manifest-Resources-Tests","name":"MFClassB>>#method3"},{"package":"KernelTests","name":"BlockClosureTest>>#testOnForkErrorTakesLessThanOneSecond"},{"package":"Compiler","name":"VariableNode>>#sizeCodeForValue:"},{"package":"Compiler","name":"VariableNode>>#emitCodeForValue:encoder:"},{"package":"Morphic-Widgets-FastTable","name":"FTPluggableIconListMorphAdaptor>>#scrollValue"},{"package":"SUnit-UITesting","name":"UITestCase>>#runCase"},{"package":"Files","name":"Stdio class>>#standardIOStreamNamed:forWrite:"},{"package":"GT-Spotter","name":"GTSpotterWidgetThemer>>#itemIconStyleFor:"},{"package":"Compression","name":"ZipWriteStream class>>#printRegressionStats:from:"},{"package":"Compression","name":"ZipWriteStream class>>#regressionTestFrom:"},{"package":"Compression","name":"ZipWriteStream class>>#compressAndDecompress:using:stats:"},{"package":"MonticelloGUI","name":"MCConfigurationBrowser>>#showChangeLog"},{"package":"Rubric","name":"RubTextEditor>>#saveContentsInFile"},{"package":"Rubric","name":"RubTextEditor>>#inOutdent:delta:"},{"package":"Rubric","name":"RubTextEditor>>#setIndices:forward:"},{"package":"FileSystem-Tests-Core","name":"FileLocatorTest>>#testResolveRelativeReference"},{"package":"GT-Playground","name":"GTPlayground class>>#edit:label:"},{"package":"Metacello-MC","name":"MetacelloFetchingMCSpecLoader>>#resolveDependencies:nearest:into:"},{"package":"Monticello","name":"MCTraitDefinition>>#="},{"package":"Compiler","name":"LiteralVariableNode>>#emitCodeForStore:encoder:"},{"package":"KernelTests","name":"DelayBenchmark>>#bench"},{"package":"Kernel","name":"Behavior>>#instSize"},{"package":"Glamour-Rubric-Presentations","name":"GLMLipsumWithSegmentsExample>>#presentation"},{"package":"Glamour-Core","name":"GLMPresentation>>#status:"},{"package":"Glamour-Core","name":"GLMPresentation>>#registerAnnouncements"},{"package":"Glamour-Core","name":"GLMPresentation>>#postCopy"},{"package":"Glamour-Core","name":"GLMPresentation>>#copy"},{"package":"OpalCompiler-Core","name":"IRSequence>>#splitAfter:"},{"package":"GT-Tests-Spotter","name":"GLMMockPagerModel>>#popPane:"},{"package":"GT-Tests-Spotter","name":"GLMMockPagerModel>>#scrollToPane:callback:"},{"package":"GT-SpotterExtensions-Core","name":"HelpTopic>>#spotterPreviewSubtopicsHelpIn:"},{"package":"GT-SpotterExtensions-Core","name":"HelpTopic>>#spotterPreviewContentHelpIn:"},{"package":"GT-SpotterExtensions-Core","name":"HelpTopic>>#spotterForHelpTopicFor:"},{"package":"Morphic-Base","name":"MenuMorph>>#addWithLabel:enablement:action:"},{"package":"Morphic-Base","name":"MenuMorph>>#addUpdating:target:selector:argumentList:"},{"package":"GT-SpotterExtensions-Core","name":"MenuMorph>>#spotterItemsFor:"},{"package":"Morphic-Widgets-NewList","name":"NewList>>#updateRenderer"},{"package":"Kernel","name":"Context class>>#trace:"},{"package":"Morphic-Widgets-Tabs","name":"Tab>>#mouseDown:"},{"package":"Ring-Core-Kernel","name":"RGCommentDefinition>>#selector"},{"package":"Ring-Core-Kernel","name":"RGCommentDefinition>>#methodClass"},{"package":"Morphic-Base","name":"HandleMorph>>#keyStroke:"},{"package":"Morphic-Base","name":"HandleMorph>>#justDroppedInto:event:"},{"package":"Morphic-Base","name":"HandleMorph>>#startStepping"},{"package":"Kernel","name":"Object>>#haltIf:"},{"package":"NativeBoost-Core","name":"Object>>#nbLibraryNameOrHandle"},{"package":"Kernel","name":"Object>>#halt:"},{"package":"Kernel","name":"Object>>#log:"},{"package":"Kernel","name":"Object>>#haltIfShiftPressed"},{"package":"GT-Spotter","name":"Object>>#spotterPreviewRawIn:"},{"package":"Kernel","name":"Object>>#haltOnCount:"},{"package":"Kernel","name":"Object>>#halt"},{"package":"Kernel","name":"Object>>#nominallyUnsent:"},{"package":"Kernel","name":"Object>>#trace:"},{"package":"Tool-Base","name":"Object>>#inspectOnce"},{"package":"Kernel","name":"Object>>#haltOnce"},{"package":"GT-SpotterExtensions-Core","name":"MetacelloProject>>#spotterForVersionsFor:"},{"package":"Metacello-Core","name":"MetacelloProject>>#latestVersion"},{"package":"Morphic-Widgets-NewList","name":"NewListRenderer>>#updateRectFor:and:"},{"package":"Morphic-Widgets-NewList","name":"NewListRenderer>>#updateRectFor:"},{"package":"Morphic-Widgets-NewList","name":"NewListRenderer>>#drawItem:at:on:"},{"package":"Reflectivity","name":"LinkWrapper>>#emitValue:"},{"package":"OpalCompiler-Core","name":"OCASTTranslator>>#visitBlockNode:"},{"package":"AsmJit-StackManagement","name":"AJReserveTemp>>#prohibitsRex"},{"package":"System-CommandLine","name":"VTermOutputDriver>>#here"},{"package":"System-CommandLine","name":"VTermOutputDriver>>#overwrite:"},{"package":"GT-Spotter","name":"GTSpotterContext>>#exceptionHandler"},{"package":"Morphic-Base","name":"SystemProgressMorph class>>#show:from:to:during:"},{"package":"Morphic-Base","name":"SystemProgressMorph class>>#show:from:to:"},{"package":"Morphic-Base","name":"SystemProgressMorph class>>#endJob:"},{"package":"Monticello","name":"MCStReader>>#classInstVarNamesFor:"},{"package":"Rubric","name":"RubTextSegmentMorph>>#textChangedFrom:to:delta:"},{"package":"Tool-TxWorkspace","name":"TxWorkspace>>#updateSyntaxHighlighting"},{"package":"Glamour-Morphic-Widgets","name":"GLMTreeMorphNodeModel>>#shouldBeDisplayedByText"},{"package":"Glamour-Morphic-Widgets","name":"GLMTreeMorphNodeModel>>#shouldBeDisplayedByTags"},{"package":"Balloon","name":"BalloonBezierSimulation>>#quickPrint:first:"},{"package":"OpalCompiler-Core","name":"IRBuilder>>#addBlockReturnTopIfRequired"},{"package":"DebuggerModel","name":"DebugSession class>>#debuggingActionsForPragmas:for:"},{"package":"Graphics-Fonts","name":"StrikeFont>>#characters:in:displayAt:clippedBy:rule:fillColor:kernDelta:on:"},{"package":"Tests","name":"TraitTest>>#testRemoveFromSystem"},{"package":"Tests","name":"TraitTest>>#testTraitRemoval"},{"package":"Morphic-Base","name":"TextMorphForEditView>>#mouseDown:"},{"package":"OpalCompiler-Tests","name":"OCCompilerTest>>#testInBlockArgumentInstanceVariableShadowing"},{"package":"Spec-Debugger","name":"DebugAction>>#shortcutCommand"},{"package":"Manifest-Core","name":"SmalllintManifestChecker>>#runRules:onPackage:withoutTestCase:"},{"package":"Metacello-Core","name":"MetacelloVersionValidator>>#recordValidationCriticalWarning:versionString:callSite:reasonCode:"},{"package":"Metacello-Core","name":"MetacelloVersionValidator>>#recordValidationError:versionString:callSite:reasonCode:"},{"package":"Metacello-Core","name":"MetacelloVersionValidator>>#recordValidationWarning:versionString:callSite:reasonCode:"},{"package":"Slot","name":"AbstractLayout>>#resolveSlot:"},{"package":"Glamour-Morphic-Pager","name":"GLMPagerButtonsPaneBrick>>#markButtonsInside:"},{"package":"GT-Playground","name":"GTPlayBook>>#initialize"},{"package":"Spec-Debugger","name":"SpecDebugger class>>#informExistingDebugger:label:"},{"package":"Athens-Morphic","name":"AthensParagraph>>#secondarySelection:"},{"package":"Athens-Morphic","name":"AthensParagraph>>#extraSelectionChanged"},{"package":"Athens-Morphic","name":"AthensParagraph>>#findReplaceSelectionRegex:"},{"package":"Glamour-Morphic-Widgets","name":"GLMTextMorphForEditView>>#acceptContents"},{"package":"Glamour-Morphic-Renderer","name":"GLMMorphicPaneRenderer>>#actOnMatchingPresentationChanged:"},{"package":"Glamour-Morphic-Renderer","name":"GLMMorphicListingRenderer>>#actOnUpdatedPresentation:"},{"package":"Zinc-HTTP","name":"ZnMessage>>#writeToTranscript"},{"package":"Keymapping-Core","name":"KMLog class>>#log:"},{"package":"EmergencyEvaluator","name":"Transcripter class>>#startTranscriptProcess"},{"package":"Glamour-Morphic-Renderer","name":"GLMMorphicSmalltalkCodeRenderer>>#actOnVariableBindingsUpdated:"},{"package":"Glamour-Examples","name":"GLMBasicExamples>>#interdependentPanes"},{"package":"Glamour-Examples","name":"GLMBasicExamples>>#onChangeOfPortAction"},{"package":"Glamour-Examples","name":"GLMBasicExamples>>#wizard"},{"package":"UpdateStreamer-Core","name":"UpdateStreamer>>#groupUpdatesByVersion:"},{"package":"UpdateStreamer-Core","name":"UpdateStreamer>>#extractVersion:from:"},{"package":"Fuel","name":"FLLightGeneralMapper>>#visitCharacter:"},{"package":"Balloon","name":"BalloonEngine class>>#printStats"},{"package":"FileSystem-Disk","name":"FileHandle>>#open"},{"package":"FileSystem-Disk","name":"FileHandle>>#at:write:startingAt:count:"},{"package":"FileSystem-Disk","name":"FileHandle>>#at:read:startingAt:count:"},{"package":"FileSystem-Disk","name":"FileHandle>>#flush"},{"package":"FileSystem-Disk","name":"FileHandle>>#size"},{"package":"GT-Spotter","name":"GTFilter>>#exceptionHandler"},{"package":"Collections-Strings","name":"String>>#isLiteralSymbol"}]},{"name":"RBSentNotImplementedRule","severity":null,"group":null,"critics":[]},{"name":"RBMethodSourceContainsLinefeedsRule","severity":null,"group":null,"critics":[]},{"name":"RBSendsMethodDictRule","severity":null,"group":null,"critics":[]},{"name":"RBOverridesSpecialMessageRule","severity":null,"group":null,"critics":[]},{"name":"RBUndeclaredReferenceRule","severity":null,"group":null,"critics":[]},{"name":"RBSuperSendsNewRule","severity":null,"group":null,"critics":[]},{"name":"RBSendsUnknownMessageToGlobalRule","severity":null,"group":null,"critics":[]},{"name":"RBSubclassResponsibilityNotDefinedRule","severity":null,"group":null,"critics":[]},{"name":"RBUsesTrueRule","severity":null,"group":null,"critics":[]},{"name":"RBVariableNotDefinedRule","severity":null,"group":null,"critics":[]},{"name":"RBAsOrderedCollectionNotNeededRule","severity":null,"group":null,"critics":[]},{"name":"RBExtraBlockRule","severity":null,"group":null,"critics":[]},{"name":"RBEndTrueFalseRule","severity":null,"group":null,"critics":[]},{"name":"RBTrueFalseDuplicationRule","severity":null,"group":null,"critics":[]},{"name":"RBCollectSelectNotUsedRule","severity":null,"group":null,"critics":[]},{"name":"RBYourselfNotUsedRule","severity":null,"group":null,"critics":[]},{"name":"RBNotEliminationRule","severity":null,"group":null,"critics":[]},{"name":"RBOnlyReadOrWrittenVariableRule","severity":null,"group":null,"critics":[]},{"name":"RBLiteralArrayCharactersRule","severity":null,"group":null,"critics":[]},{"name":"RBJustSendsSuperRule","severity":null,"group":null,"critics":[]},{"name":"RBUnwindBlocksRule","severity":null,"group":null,"critics":[]},{"name":"RBAssignmentInIfTrueRule","severity":null,"group":null,"critics":[]},{"name":"RBRemoveAssignmentWithoutEffectRule","severity":null,"group":null,"critics":[]},{"name":"RBLocalMethodsOfAClassNotInItsTraitComposition","severity":null,"group":null,"critics":[]},{"name":"RBStringConcatenationRule","severity":null,"group":null,"critics":[]},{"name":"RBOnlyReadOrWrittenTemporaryRule","severity":null,"group":null,"critics":[]},{"name":"RBEqualsTrueRule","severity":null,"group":null,"critics":[]},{"name":"RBUnnecessaryAssignmentRule","severity":null,"group":null,"critics":[]},{"name":"RBSizeCheckRule","severity":null,"group":null,"critics":[]},{"name":"RBUnoptimizedAndOrRule","severity":null,"group":null,"critics":[]},{"name":"RBUnoptimizedToDoRule","severity":null,"group":null,"critics":[]},{"name":"RBContainsRule","severity":null,"group":null,"critics":[]},{"name":"RBSearchingLiteralRule","severity":null,"group":null,"critics":[]},{"name":"RBIfTrueReturnsRule","severity":null,"group":null,"critics":[]},{"name":"RBkeysDoRule","severity":null,"group":null,"critics":[]},{"name":"RBFileBlocksRule","severity":null,"group":null,"critics":[]},{"name":"RBAssignmentOnBlockArgumentRule","severity":null,"group":null,"critics":[]},{"name":"RBDoNotSendSuperInitializeInClassSideRule","severity":null,"group":null,"critics":[]},{"name":"RBReturnInEnsureRule","severity":null,"group":null,"critics":[]},{"name":"RBDefinesEqualNotHashRule","severity":null,"group":null,"critics":[]},{"name":"RBEqualNotUsedRule","severity":null,"group":null,"critics":[]},{"name":"RBEmptyExceptionHandlerRule","severity":null,"group":null,"critics":[]},{"name":"RBFloatEqualityComparisonRule","severity":null,"group":null,"critics":[]},{"name":"RBClassInstVarNotInitializedRule","severity":null,"group":null,"critics":[]},{"name":"RBPrecedenceRule","severity":null,"group":null,"critics":[]},{"name":"RBTempVarOverridesInstVarRule","severity":null,"group":null,"critics":[]},{"name":"RBLiteralArrayContainsSuspiciousTrueFalseOrNilRule","severity":null,"group":null,"critics":[]},{"name":"RBMissingSuperSendsRule","severity":null,"group":null,"critics":[]},{"name":"RBModifiesCollectionRule","severity":null,"group":null,"critics":[]},{"name":"RBAddRemoveDependentsRule","severity":null,"group":null,"critics":[]},{"name":"RBPlatformDependentUserInteractionRule","severity":null,"group":null,"critics":[]},{"name":"RBMissingYourselfRule","severity":null,"group":null,"critics":[]},{"name":"RBThreeElementPointRule","severity":null,"group":null,"critics":[]},{"name":"RBAbstractClassRule","severity":null,"group":null,"critics":[]},{"name":"RBReturnsBooleanAndOtherRule","severity":null,"group":null,"critics":[]},{"name":"RBReturnsIfTrueRule","severity":null,"group":null,"critics":[]},{"name":"RBCollectionCopyEmptyRule","severity":null,"group":null,"critics":[]},{"name":"RBTempsReadBeforeWrittenRule","severity":null,"group":null,"critics":[]},{"name":"RBUnaryAccessingMethodWithoutReturnRule","severity":null,"group":null,"critics":[]},{"name":"RBUncommonMessageSendRule","severity":null,"group":null,"critics":[]},{"name":"RBUnconditionalRecursionRule","severity":null,"group":null,"critics":[]},{"name":"RBUnpackagedCodeRule","severity":null,"group":null,"critics":[]},{"name":"RBBooleanPrecedenceRule","severity":null,"group":null,"critics":[]},{"name":"RBUsesAddRule","severity":null,"group":null,"critics":[]},{"name":"RBClassNotReferencedRule","severity":null,"group":null,"critics":[]},{"name":"RBExcessiveInheritanceRule","severity":null,"group":null,"critics":[]},{"name":"RBExcessiveArgumentsRule","severity":null,"group":null,"critics":[]},{"name":"RBExcessiveMethodsRule","severity":null,"group":null,"critics":[]},{"name":"RBExcessiveVariablesRule","severity":null,"group":null,"critics":[]},{"name":"RBFutureDeprecationWarningRule","severity":null,"group":null,"critics":[]},{"name":"RBInconsistentMethodClassificationRule","severity":null,"group":null,"critics":[]},{"name":"RBInstVarInSubclassesRule","severity":null,"group":null,"critics":[]},{"name":"RBLongMethodsRule","severity":null,"group":null,"critics":[]},{"name":"RBMissingSubclassResponsibilityRule","severity":null,"group":null,"critics":[]},{"name":"RBEquivalentSuperclassMethodsRule","severity":null,"group":null,"critics":[]},{"name":"RBImplementedNotSentRule","severity":null,"group":null,"critics":[]},{"name":"RBRefersToClassRule","severity":null,"group":null,"critics":[]},{"name":"RBSuperSendsRule","severity":null,"group":null,"critics":[]},{"name":"RBSendsDeprecatedMethodToGlobalRule","severity":null,"group":null,"critics":[]},{"name":"RBSendsDifferentSuperRule","severity":null,"group":null,"critics":[]},{"name":"RBVariableAssignedLiteralRule","severity":null,"group":null,"critics":[]},{"name":"RBVariableReferencedOnceRule","severity":null,"group":null,"critics":[]},{"name":"RBUnreferencedVariablesRule","severity":null,"group":null,"critics":[]},{"name":"RBClassVariableCapitalizationRule","severity":null,"group":null,"critics":[]},{"name":"RBInstanceVariableCapitalizationRule","severity":null,"group":null,"critics":[]},{"name":"RBClassNameInSelectorRule","severity":null,"group":null,"critics":[]},{"name":"RBTemporaryVariableCapitalizationRule","severity":null,"group":null,"critics":[]},{"name":"RBUnclassifiedMethodsRule","severity":null,"group":null,"critics":[]},{"name":"RBUnderscoreAssignmentRule","severity":null,"group":null,"critics":[]},{"name":"RBDeprecateWithFirstCharacterDownshifted","severity":null,"group":null,"critics":[]},{"name":"RBBetweenAndRule","severity":null,"group":null,"critics":[]},{"name":"RBDetectIfNoneRule","severity":null,"group":null,"critics":[]},{"name":"RBEqualNilRule","severity":null,"group":null,"critics":[]},{"name":"RBShouldntRaiseErrorRule","severity":null,"group":null,"critics":[]},{"name":"RBGuardClauseRule","severity":null,"group":null,"critics":[]},{"name":"RBExplicitRequirementMethodsRule","severity":null,"group":null,"critics":[]},{"name":"RBLiteralArrayContainsCommaRule","severity":null,"group":null,"critics":[]},{"name":"RBNoClassCommentRule","severity":null,"group":null,"critics":[]},{"name":"RBAllAnyNoneSatisfyRule","severity":null,"group":null,"critics":[]},{"name":"RBMinMaxRule","severity":null,"group":null,"critics":[]},{"name":"RBBadMessageRule","severity":null,"group":null,"critics":[]},{"name":"RBCollectionMessagesToExternalObjectRule","severity":null,"group":null,"critics":[]},{"name":"RBAssignmentInBlockRule","severity":null,"group":null,"critics":[]},{"name":"RBThemeAPIUpdateRule","severity":null,"group":null,"critics":[]},{"name":"RBCascadedNextPutAllsRule","severity":null,"group":null,"critics":[]},{"name":"RBConsistencyCheckRule","severity":null,"group":null,"critics":[]},{"name":"RBCollectionProtocolRule","severity":null,"group":null,"critics":[]},{"name":"RBDetectContainsRule","severity":null,"group":null,"critics":[]},{"name":"RBToDoRule","severity":null,"group":null,"critics":[]},{"name":"RBWhileTrueRule","severity":null,"group":null,"critics":[]},{"name":"RBAtIfAbsentRule","severity":null,"group":null,"critics":[]},{"name":"RBToDoCollectRule","severity":null,"group":null,"critics":[]},{"name":"RBToDoWithIncrementRule","severity":null,"group":null,"critics":[]}]